girder_oidc/__init__.py
girder_oidc/rest.py
girder_oidc/settings.py
girder_oidc/providers/__init__.py
girder_oidc/web_client/main.js
girder_oidc/web_client/package.json
girder_oidc/web_client/routes.js
girder_oidc/web_client/stylesheets/configView.styl
girder_oidc/web_client/stylesheets/oauthLoginView.styl
girder_oidc/web_client/stylesheets/oidcUserAccountView.styl
girder_oidc/web_client/templates/configView.pug
girder_oidc/web_client/templates/oauthLoginView.pug
girder_oidc/web_client/templates/oidcUserAccountView.pug
girder_oidc/web_client/views/ConfigView.js
girder_oidc/web_client/views/LoginView.js
girder_oidc/web_client/views/SettingsInterceptor.js
plugin_tests/README.md
plugin_tests/__init__.py
plugin_tests/conftest.py
plugin_tests/test_configuration.py
plugin_tests/test_provider.py
plugin_tests/test_rest_endpoints.py
plugin_tests/test_token_get.py
plugin_tests/test_user_management.py
girder_oidc-0.0.2.dist-info/METADATA
girder_oidc-0.0.2.dist-info/WHEEL
girder_oidc-0.0.2.dist-info/entry_points.txt
girder_oidc-0.0.2.dist-info/top_level.txt
girder_oidc-0.0.2.dist-info/RECORD
