Metadata-Version: 2.4
Name: girder-oidc
Version: 0.0.2
Summary: Girder plugin for OIDC/Keycloak authentication
Author: Josselin Duchateau
License: Apache 2.0
Project-URL: Homepage, https://github.com/girder/girder-oidc
Keywords: girder,oidc,keycloak,authentication
Classifier: Development Status :: 4 - Beta
Classifier: License :: OSI Approved :: Apache Software License
Classifier: Natural Language :: English
Classifier: Programming Language :: Python :: 3
Requires-Dist: girder>=3.0.0
Requires-Dist: python-jose[cryptography]
Requires-Dist: requests
